django_codemod/__init__.py
django_codemod/cli.py
django_codemod/commands.py
django_codemod/constants.py
django_codemod/feature_flags.py
django_codemod/path_utils.py
django_codemod/utils/__init__.py
django_codemod/utils/calls.py
django_codemod/visitors/__init__.py
django_codemod/visitors/admin.py
django_codemod/visitors/base.py
django_codemod/visitors/core.py
django_codemod/visitors/crypto.py
django_codemod/visitors/decorators.py
django_codemod/visitors/encoding.py
django_codemod/visitors/exceptions.py
django_codemod/visitors/forms.py
django_codemod/visitors/html.py
django_codemod/visitors/http.py
django_codemod/visitors/lru_cache.py
django_codemod/visitors/models.py
django_codemod/visitors/os_utils.py
django_codemod/visitors/paginator.py
django_codemod/visitors/postgres_fields.py
django_codemod/visitors/shortcuts.py
django_codemod/visitors/signals.py
django_codemod/visitors/template_context.py
django_codemod/visitors/template_tags.py
django_codemod/visitors/timezone.py
django_codemod/visitors/translations.py
django_codemod/visitors/urls.py
django_codemod-2.4.5.dist-info/licenses/LICENSE
django_codemod-2.4.5.dist-info/METADATA
django_codemod-2.4.5.dist-info/WHEEL
django_codemod-2.4.5.dist-info/entry_points.txt
django_codemod-2.4.5.dist-info/top_level.txt
django_codemod-2.4.5.dist-info/RECORD
