Metadata-Version: 2.4
Name: django-codemod
Version: 2.4.5
Summary: A command line tool to automatically fix Django deprecations.
Author-email: Bruno Alla <alla.brunoo@gmail.com>
License-Expression: MIT
Project-URL: Bug Tracker, https://github.com/browniebroke/django-codemod/issues
Project-URL: Changelog, https://django-codemod.readthedocs.io/en/stable/changelog.html
Project-URL: documentation, https://django-codemod.readthedocs.io
Project-URL: Mastodon, https://fosstodon.org/@browniebroke
Project-URL: repository, https://github.com/browniebroke/django-codemod
Project-URL: Twitter, https://twitter.com/_BrunoAlla
Keywords: codemod,django,libCST
Classifier: Development Status :: 5 - Production/Stable
Classifier: Intended Audience :: Developers
Classifier: Natural Language :: English
Classifier: Operating System :: OS Independent
Classifier: Programming Language :: Python :: 3 :: Only
Classifier: Programming Language :: Python :: 3.10
Classifier: Programming Language :: Python :: 3.11
Classifier: Programming Language :: Python :: 3.12
Classifier: Programming Language :: Python :: 3.13
Classifier: Programming Language :: Python :: 3.14
Classifier: Topic :: Software Development :: Libraries
Requires-Python: >=3.10
License-File: LICENSE
Requires-Dist: click<8.4
Requires-Dist: libcst==1.8.6
Requires-Dist: pathspec<2,>=0.6
Requires-Dist: rich>=10
Requires-Dist: rich-click>=1
Dynamic: license-file
